{
  "type": "minecraft:chest",
  "pools": [
    {
      "rolls": 1,
      "entries": [
        {
          "type": "minecraft:item",
          "name": "minecraft:wooden_pickaxe",
          "weight": 2
        },
        {
          "type": "minecraft:item",
          "name": "minecraft:stone_pickaxe",
          "weight": 4
        },
        {
          "type": "minecraft:item",
          "name": "minecraft:iron_pickaxe",
          "weight": 6
        },
        {
          "type": "minecraft:item",
          "name": "minecraft:golden_pickaxe",
          "weight": 4
        },
        {
          "type": "minecraft:item",
          "name": "minecraft:diamond_pickaxe",
          "weight": 1
        },

        {
          "type": "minecraft:item",
          "name": "minecraft:wooden_axe",
          "weight": 1
        },
        {
          "type": "minecraft:item",
          "name": "minecraft:stone_axe",
          "weight": 2
        },
        {
          "type": "minecraft:item",
          "name": "minecraft:iron_axe",
          "weight": 3
        },
        {
          "type": "minecraft:item",
          "name": "minecraft:golden_axe",
          "weight": 2
        },
        {
          "type": "minecraft:item",
          "name": "minecraft:diamond_axe",
          "weight": 1
        },

        {
          "type": "minecraft:item",
          "name": "minecraft:wooden_shovel",
          "weight": 1
        },
        {
          "type": "minecraft:item",
          "name": "minecraft:stone_shovel",
          "weight": 2
        },
        {
          "type": "minecraft:item",
          "name": "minecraft:iron_shovel",
          "weight": 3
        },
        {
          "type": "minecraft:item",
          "name": "minecraft:golden_shovel",
          "weight": 2
        },
        {
          "type": "minecraft:item",
          "name": "minecraft:diamond_shovel",
          "weight": 1
        },

        {
          "type": "minecraft:item",
          "name": "minecraft:water_bucket",
          "weight": 1
        }
      ]
    },
    {
      "rolls": {
        "min": 0,
        "max": 1
      },
      "entries": [
        {
          "type": "minecraft:item",
          "name": "minecraft:wooden_sword",
          "weight": 1
        },
        {
          "type": "minecraft:item",
          "name": "minecraft:stone_sword",
          "weight": 2
        },
        {
          "type": "minecraft:item",
          "name": "minecraft:golden_sword",
          "weight": 2
        },
        {
          "type": "minecraft:item",
          "name": "minecraft:diamond_sword",
          "weight": 1
        }
      ]
    },
    {
      "rolls": {
        "min": 3,
        "max": 5
      },
      "entries": [
        {
          "type": "minecraft:item",
          "name": "minecraft:oak_log",
          "weight": 2,
          "functions": [
            {
              "function": "minecraft:set_count",
              "count": {
                "type": "minecraft:binomial",
                "n": 20,
                "p": 0.5
              }
            }
          ]
        },
        {
          "type": "minecraft:item",
          "name": "minecraft:stone",
          "weight": 3,
          "functions": [
            {
              "function": "minecraft:set_count",
              "count": {
                "type": "minecraft:binomial",
                "n": 20,
                "p": 0.5
              }
            }
          ]
        },
        {
          "type": "minecraft:item",
          "name": "minecraft:iron_ingot",
          "weight": 4,
          "functions": [
            {
              "function": "minecraft:set_count",
              "count": {
                "type": "minecraft:binomial",
                "n": 14,
                "p": 0.5
              }
            }
          ]
        },
        {
          "type": "minecraft:item",
          "name": "minecraft:diamond",
          "weight": 1,
          "functions": [
            {
              "function": "minecraft:set_count",
              "count": {
                "type": "minecraft:binomial",
                "n": 5,
                "p": 0.2
              }
            }
          ]
        }
      ]
    }
  ]
}